fastest_asyncapi/__init__.py
fastest_asyncapi/templates/v3/asyncapi.html
fastest_asyncapi/utils.py
fastest_asyncapi/views/__init__.py
fastest_asyncapi/views/async/__init__.py
fastest_asyncapi/views/sync/__init__.py
fastest_asyncapi/views/sync/v3/__init__.py
fastest_asyncapi/views/sync/v3/asyncapi.py
fastest_asyncapi-0.1.5.dist-info/LICENSE
fastest_asyncapi-0.1.5.dist-info/METADATA
fastest_asyncapi-0.1.5.dist-info/WHEEL
fastest_asyncapi-0.1.5.dist-info/RECORD
