Metadata-Version: 2.3
Name: fastest-asyncapi
Version: 0.1.5
Summary: 
Author: Sergei Konik
Author-email: s.konik.dev@gmail.com
Requires-Python: >=3.11,<4.0
Classifier: Programming Language :: Python :: 3
Classifier: Programming Language :: Python :: 3.11
Classifier: Programming Language :: Python :: 3.12
Classifier: Programming Language :: Python :: 3.13
Requires-Dist: asyncapi-container (==0.4.4)
Requires-Dist: fastapi (>=0.109.0)
Requires-Dist: jinja2 (>=3.1.3,<4.0.0)
Requires-Dist: uvicorn (>=0.27.0,<0.28.0)
